Metadata-Version: 2.1
Name: pyppdf
Version: 0.0.9
Summary: Pyppeteer PDF. Print html sites and files to pdf via pyppeteer (uses patched pyppeteer that by default downloads updated Chromium revision via https with certifi).
Home-page: https://github.com/kiwi0fruit/pyppdf
Author: Peter Zagubisalo
Author-email: peter.zagubisalo@gmail.com
License: MIT
Platform: UNKNOWN
Classifier: Development Status :: 3 - Alpha
Classifier: Intended Audience :: Developers
Classifier: Topic :: Software Development :: Build Tools
Classifier: License :: OSI Approved :: MIT License
Classifier: Programming Language :: Python :: 3
Classifier: Programming Language :: Python :: 3.6
Requires-Python: >=3.6
